{
  "version": 2,
  "architecture": "aarch64_generic",
  "packages": {
    "3ginfo": "20250327-r1",
    "3ginfo-lite": "20250327-r1",
    "3ginfo-old": "20250327-r1",
    "3ginfo-qmisignal": "20250327-r1",
    "3ginfo-text": "20250327-r1",
    "3ginfo-text-old": "20250327-r1",
    "3proxy": "0.9.5-r6",
    "3proxy-common": "0.9.5-r6",
    "3proxy-sql": "0.9.5-r6",
    "7z": "24.09-r1",
    "atinout": "0.9.1",
    "autoshare-ksmbd": "1-r2",
    "autoshare-samba": "1-r2",
    "cpufreq": "2",
    "internet-detector": "1.5.1-r15",
    "internet-detector-mod-email": "1.5.1-r15",
    "internet-detector-mod-modem-restart": "1.5.1-r14",
    "lib3proxy": "0.9.5-r6",
    "luci-app-3ginfo-lite": "1.0.74-r9",
    "luci-app-adguardhome": "25.179.44715~d076b6d",
    "luci-app-alpha-config": "2.1-r3",
    "luci-app-amlogic": "3.1.253-r15",
    "luci-app-argon-config": "25.179.44715~d076b6d",
    "luci-app-atcommands": "1.0.9-r6",
    "luci-app-atinout": "0.1.0-r6",
    "luci-app-autoreboot": "1.0-r6",
    "luci-app-change-mac": "0.3.9-r1",
    "luci-app-cpu-status": "0.6.1-r7",
    "luci-app-cpu-status-mini": "0.2.0-r4",
    "luci-app-cpufreq": "25.179.44715~d076b6d",
    "luci-app-cpulimit": "25.179.44715~d076b6d",
    "luci-app-diskman": "0.2.11-r2",
    "luci-app-disks-info": "0.4.2-r5",
    "luci-app-droidmodem": "1.1-r10",
    "luci-app-droidnet": "1.1-r13",
    "luci-app-eqosplus": "1.2.5-r16",
    "luci-app-interfaces-statistics": "0.4.0-r3",
    "luci-app-internet-detector": "1.5.1-r14",
    "luci-app-iperf": "25.179.44715~d076b6d",
    "luci-app-iperf3-server": "2.0-r12",
    "luci-app-ipinfo": "2.4-r6",
    "luci-app-lite-watchdog": "1.0.15-r6",
    "luci-app-log-viewer": "1.3.0-r11",
    "luci-app-mac": "4.2.1-r5",
    "luci-app-macvlan": "1.0.0-r7",
    "luci-app-modemband": "1.0.24-r8",
    "luci-app-modeminfo": "0.4.3-r10",
    "luci-app-netdata": "25.179.44715~d076b6d",
    "luci-app-netspeedtest": "5.0.5-r14",
    "luci-app-oled": "25.179.44715~d076b6d",
    "luci-app-poweroffdevice": "2-r6",
    "luci-app-pppoe-relay": "1.0-r7",
    "luci-app-pppoe-server": "20200326-r8",
    "luci-app-pppoe-user": "1.0-r14",
    "luci-app-pptp-server": "1.0-r11",
    "luci-app-pptpd": "25.179.44715~d076b6d",
    "luci-app-ramfree": "1.0-r2",
    "luci-app-rclone": "1.4.1-r8",
    "luci-app-shutdown": "1.0-r2",
    "luci-app-smbuser": "1.0-r5",
    "luci-app-sms-tool": "1.0.0-r9",
    "luci-app-sms-tool-js": "2.0.24-r8",
    "luci-app-speedtest-web": "1.0-r6",
    "luci-app-tailscale": "25.179.44715~d076b6d",
    "luci-app-telegrambot": "0.1.0-r2",
    "luci-app-temp-status": "0.5.6-r18",
    "luci-app-tinyfilemanager": "2.6-r14",
    "luci-app-usb-printer": "1.0-r6",
    "luci-app-watchdog": "1.0.4-r4",
    "luci-app-zerotier": "25.179.44715~d076b6d",
    "luci-i18n-3ginfo-lite-de": "25.179.44715~d076b6d",
    "luci-i18n-3ginfo-lite-it": "25.179.44715~d076b6d",
    "luci-i18n-3ginfo-lite-pl": "25.179.44715~d076b6d",
    "luci-i18n-3ginfo-lite-ru": "25.179.44715~d076b6d",
    "luci-i18n-3ginfo-lite-zh-cn": "25.179.44715~d076b6d",
    "luci-i18n-adguardhome-zh-cn": "25.179.44715~d076b6d",
    "luci-i18n-amlogic-zh-cn": "25.179.44715~d076b6d",
    "luci-i18n-argon-config-zh-cn": "25.179.44715~d076b6d",
    "luci-i18n-atcommands-it": "25.179.44715~d076b6d",
    "luci-i18n-atcommands-pl": "25.179.44715~d076b6d",
    "luci-i18n-atcommands-zh-cn": "25.179.44715~d076b6d",
    "luci-i18n-atinout-ru": "25.179.44715~d076b6d",
    "luci-i18n-atinout-zh-cn": "25.179.44715~d076b6d",
    "luci-i18n-autoreboot-zh-cn": "25.179.44715~d076b6d",
    "luci-i18n-change-mac-zh-cn": "25.179.44715~d076b6d",
    "luci-i18n-change-mac-zh-tw": "25.179.44715~d076b6d",
    "luci-i18n-cpu-status-mini-ru": "25.179.44715~d076b6d",
    "luci-i18n-cpu-status-ru": "25.179.44715~d076b6d",
    "luci-i18n-cpu-status-zh-cn": "25.179.44715~d076b6d",
    "luci-i18n-cpu-status-zh-tw": "25.179.44715~d076b6d",
    "luci-i18n-cpufreq-zh-cn": "25.179.44715~d076b6d",
    "luci-i18n-cpulimit-zh-cn": "25.179.44715~d076b6d",
    "luci-i18n-diskman-pl": "25.179.44715~d076b6d",
    "luci-i18n-diskman-zh-cn": "25.179.44715~d076b6d",
    "luci-i18n-diskman-zh-tw": "25.179.44715~d076b6d",
    "luci-i18n-disks-info-ru": "25.179.44715~d076b6d",
    "luci-i18n-disks-info-zh-cn": "25.179.44715~d076b6d",
    "luci-i18n-eqosplus-zh-cn": "25.179.44715~d076b6d",
    "luci-i18n-interfaces-statistics-ru": "25.179.44715~d076b6d",
    "luci-i18n-interfaces-statistics-zh-cn": "25.179.44715~d076b6d",
    "luci-i18n-internet-detector-ru": "25.179.44715~d076b6d",
    "luci-i18n-iperf-de": "25.179.44715~d076b6d",
    "luci-i18n-iperf-fr": "25.179.44715~d076b6d",
    "luci-i18n-iperf-it": "25.179.44715~d076b6d",
    "luci-i18n-iperf-ru": "25.179.44715~d076b6d",
    "luci-i18n-iperf-zh-cn": "25.179.44715~d076b6d",
    "luci-i18n-iperf3-server-zh-cn": "25.179.44715~d076b6d",
    "luci-i18n-lite-watchdog-pl": "25.179.44715~d076b6d",
    "luci-i18n-log-ru": "25.179.44715~d076b6d",
    "luci-i18n-log-zh-cn": "25.179.44715~d076b6d",
    "luci-i18n-modemband-pl": "25.179.44715~d076b6d",
    "luci-i18n-modemband-zh-cn": "25.179.44715~d076b6d",
    "luci-i18n-modeminfo-ru": "25.179.44715~d076b6d",
    "luci-i18n-modeminfo-zh-cn": "25.179.44715~d076b6d",
    "luci-i18n-netdata-zh-cn": "25.179.44715~d076b6d",
    "luci-i18n-netdata-zh-tw": "25.179.44715~d076b6d",
    "luci-i18n-netspeedtest-zh-cn": "25.179.44715~d076b6d",
    "luci-i18n-oled-zh-cn": "25.179.44715~d076b6d",
    "luci-i18n-oled-zh-tw": "25.179.44715~d076b6d",
    "luci-i18n-poweroffdevice-zh-cn": "25.179.44715~d076b6d",
    "luci-i18n-pppoe-relay-zh-cn": "25.179.44715~d076b6d",
    "luci-i18n-pppoe-server-zh-cn": "25.179.44715~d076b6d",
    "luci-i18n-pppoe-user-zh-cn": "25.179.44715~d076b6d",
    "luci-i18n-pptp-server-zh-cn": "25.179.44715~d076b6d",
    "luci-i18n-pptpd-zh-cn": "25.179.44715~d076b6d",
    "luci-i18n-ramfree-zh-cn": "25.179.44715~d076b6d",
    "luci-i18n-rclone-zh-cn": "25.179.44715~d076b6d",
    "luci-i18n-shutdown-zh-cn": "25.179.44715~d076b6d",
    "luci-i18n-smbuser-zh-cn": "25.179.44715~d076b6d",
    "luci-i18n-sms-tool-js-pl": "25.179.44715~d076b6d",
    "luci-i18n-sms-tool-js-ru": "25.179.44715~d076b6d",
    "luci-i18n-sms-tool-js-zh-cn": "25.179.44715~d076b6d",
    "luci-i18n-sms-tool-pl": "25.179.44715~d076b6d",
    "luci-i18n-sms-tool-zh-cn": "25.179.44715~d076b6d",
    "luci-i18n-speedtest-web-zh-cn": "25.179.44715~d076b6d",
    "luci-i18n-tailscale-zh-cn": "25.179.44715~d076b6d",
    "luci-i18n-telegrambot-ru": "25.179.44715~d076b6d",
    "luci-i18n-temp-status-es": "25.179.44715~d076b6d",
    "luci-i18n-temp-status-ru": "25.179.44715~d076b6d",
    "luci-i18n-temp-status-zh-cn": "25.179.44715~d076b6d",
    "luci-i18n-tinyfilemanager-zh-cn": "25.179.44715~d076b6d",
    "luci-i18n-tinyfilemanager-zh-tw": "25.179.44715~d076b6d",
    "luci-i18n-usb-printer-zh-cn": "25.179.44715~d076b6d",
    "luci-i18n-watchdog-zh-cn": "25.179.44715~d076b6d",
    "luci-i18n-zerotier-zh-cn": "25.179.44715~d076b6d",
    "luci-i18n-zerotier-zh-tw": "25.179.44715~d076b6d",
    "luci-mod-listening-ports": "1.0-r3",
    "luci-proto-quectel": "25.179.44715~d076b6d",
    "luci-proto-tun2socks": "25.179.44715~d076b6d",
    "luci-proto-wwan": "20151207-r2",
    "luci-proto-xmm": "25.179.44715~d076b6d",
    "luci-theme-argon": "2.4.2-r7",
    "modemband": "20240616-r7",
    "modeminfo": "0.4.3-r22",
    "modeminfo-qmi": "0.4.3-r22",
    "modeminfo-serial-dell": "0.4.3-r22",
    "modeminfo-serial-fibocom": "0.4.3-r22",
    "modeminfo-serial-gosun": "0.4.3-r22",
    "modeminfo-serial-huawei": "0.4.3-r22",
    "modeminfo-serial-meig": "0.4.3-r22",
    "modeminfo-serial-mikrotik": "0.4.3-r22",
    "modeminfo-serial-quectel": "0.4.3-r22",
    "modeminfo-serial-sierra": "0.4.3-r22",
    "modeminfo-serial-simcom": "0.4.3-r22",
    "modeminfo-serial-styx": "0.4.3-r22",
    "modeminfo-serial-telit": "0.4.3-r22",
    "modeminfo-serial-thales": "0.4.3-r22",
    "modeminfo-serial-tw": "0.4.3-r22",
    "modeminfo-serial-xmm": "0.4.3-r22",
    "modeminfo-serial-yuge": "0.4.3-r22",
    "modeminfo-serial-zte": "0.4.3-r22",
    "modeminfo-telegram": "0.4.3-r22",
    "netspeedtest": "1-r1",
    "ookla-speedtest": "1.2.0-r2",
    "quectel-cm": "1.6.5-r14",
    "speedtest-cli": "1.2.0-r4",
    "speedtestcli": "1.2.0-r2",
    "telegrambot": "0.0.4-r2",
    "tun2socks": "2.6.0-r21",
    "watchdog": "1-r1",
    "xmm-modem": "0.1.5-r15"
  }
}
